attributeme/__init__.py
attributeme-0.1.dist-info/LICENSE
attributeme-0.1.dist-info/METADATA
attributeme-0.1.dist-info/WHEEL
attributeme-0.1.dist-info/top_level.txt
attributeme-0.1.dist-info/RECORD
