Metadata-Version: 2.1
Name: attributeme
Version: 0.1
Summary: a pip-installable package example
Home-page: https://github.com/chugha/attributeme
Author: Aakash Chugh
Author-email: aakashchugh27@gmail.com
License: MIT
Keywords: example
Platform: UNKNOWN
